[
  { "id": 1,  "image": "Pizza.jpeg", "path": "pizza" },
  { "id": 2, "image": "Burgers.jpeg", "path": "Burgers" },
  { "id": 3,  "image": "Momos.jpeg", "path": "momos" },
  { "id": 4,  "image": "Cakes.jpeg", "path": "cakes" },
  { "id": 5,  "image": "Biryani.jpeg", "path": "biryani" },
  { "id": 6,  "image": "Rolls.jpeg", "path": "rolls" },
  { "id": 7,  "image": "Noodles.jpeg", "path": "noodles" },
  { "id": 8,  "image": "Dosa.jpeg", "path": "dosa" },
  { "id": 9,  "image": "Pasta.jpeg", "path": "pasta" },
  { "id": 10, "image": "Paratha.jpeg", "path": "paratha" },
  { "id": 11, "image": "Pastry.jpeg", "path": "pastry" },
  { "id": 12, "image": "Rasmalai.jpeg", "path": "rasmalai" },
  { "id": 13, "image": "Waffle.jpeg", "path": "waffle" },
  { "id": 14, "image": "Kebabs.jpeg", "path": "kebabs" },
  { "id": 15, "image": "Gulab_Jamun.jpeg", "path": "gulab-jamun" },
  { "id": 16, "image": "Chole_Bhature.jpeg", "path": "chole-bhature" },
  { "id": 17, "image": "Salad.jpeg", "path": "salad" },
  { "id": 18, "image": "Jalebi.jpeg", "path": "jalebi" },
  { "id": 19, "image": "Pav_Bhaji.jpeg", "path": "pav-bhaji" },
  { "id": 20, "image": "Ice_Creams.jpeg", "path": "ice-creams" }
]
